{
  "title": "Survey",
  "majorVersion": 0,
  "minorVersion": 2,
  "patchVersion": 10,
  "runnable": 1,
  "fullscreen": 1,
  "embedTypes": [
    "iframe"
  ],
  "machineName": "H5P.Survey",
  "author": "Curious Learning",
  "license": "MIT",
  "coreApi": {
    "majorVersion": 1,
    "minorVersion": 19
  },
  "preloadedJs": [
    {
      "path": "main.js"
    }
  ],
  "editorDependencies": [
    {
      "machineName": "H5PEditor.RangeList",
      "majorVersion": 1,
      "minorVersion": 0
    },
    {
      "machineName": "H5PEditor.ShowWhen",
      "majorVersion": 1,
      "minorVersion": 0
    }
  ]
}
